setup.py
qtodotxt/__init__.py
qtodotxt/app.py
qtodotxt.egg-info/PKG-INFO
qtodotxt.egg-info/SOURCES.txt
qtodotxt.egg-info/dependency_links.txt
qtodotxt.egg-info/entry_points.txt
qtodotxt.egg-info/top_level.txt
qtodotxt/lib/__init__.py
qtodotxt/lib/file.py
qtodotxt/lib/filters.py
qtodotxt/lib/task_htmlizer.py
qtodotxt/lib/tasklib.py
qtodotxt/lib/tendo_singleton.py
qtodotxt/test/__init__.py
qtodotxt/test/run-coverage.py
qtodotxt/test/run-doctests.py
qtodotxt/test/test_dates.py
qtodotxt/test/test_file.py
qtodotxt/test/test_filters_tree_controller.py
qtodotxt/test/test_htmlizer.py
qtodotxt/test/test_tasks.py
qtodotxt/ui/__init__.py
qtodotxt/ui/pyqt5_style_rc.py
qtodotxt/ui/qTodoTxt_dark_style_rc.py
qtodotxt/ui/qTodoTxt_style_rc.py
qtodotxt/ui/resource_manager.py
qtodotxt/ui/controllers/__init__.py
qtodotxt/ui/controllers/filters_tree_controller.py
qtodotxt/ui/controllers/main_controller.py
qtodotxt/ui/controllers/menu_controller.py
qtodotxt/ui/controllers/tasks_list_controller.py
qtodotxt/ui/dialogs/__init__.py
qtodotxt/ui/dialogs/about_dialog.py
qtodotxt/ui/dialogs/misc_dialogs.py
qtodotxt/ui/dialogs/settings.py
qtodotxt/ui/dialogs/settingsui.py
qtodotxt/ui/dialogs/shortcuts.py
qtodotxt/ui/dialogs/shortcutsui.py
qtodotxt/ui/dialogs/taskeditor_dialog.py
qtodotxt/ui/dialogs/taskeditor_lineedit.py
qtodotxt/ui/resources/qtodotxt.ico
qtodotxt/ui/resources/css/dark_blue.css
qtodotxt/ui/resources/css/dark_orange.css
qtodotxt/ui/views/__init__.py
qtodotxt/ui/views/filters_tree_view.py
qtodotxt/ui/views/main_view.py
qtodotxt/ui/views/tasks_list_view.py
qtodotxt/ui/views/tasks_search_view.py
qtodotxt/ui/views/tasks_view.py