Metadata-Version: 1.1
Name: qtodotxt
Version: 1.9.0
Summary: Cross Platform todo.txt GUI
Home-page: https://github.com/QTodoTxt/QTodoTxt
Author: QTT Development Team
Author-email: qtodotxt@googlegroups.com
License: GNU General Public License v3 or later
Platform: UNKNOWN
Classifier: Environment :: X11 Applications :: Qt
Classifier: Programming Language :: Python :: 3
Classifier: Development Status :: 4 - Beta
Classifier: Intended Audience :: End Users/Desktop
Classifier: Operating System :: OS Independent
Classifier: License :: OSI Approved :: GNU General Public License v3 or later (GPLv3+)
Provides: qtodotxt
